argon_88_sk/__init__.py
argon_88_sk/base.py
argon_88_sk/lib.py
argon_88_sk/serialize.py
argon_88_sk/utils/__init__.py
argon_88_sk/utils/constants.py
argon_88_sk/utils/helpers.py
argon_88_sk/utils/templates.py
argon_88_sk-0.1.2.dist-info/METADATA
argon_88_sk-0.1.2.dist-info/WHEEL
argon_88_sk-0.1.2.dist-info/entry_points.txt
argon_88_sk-0.1.2.dist-info/top_level.txt
argon_88_sk-0.1.2.dist-info/RECORD
