Metadata-Version: 2.1
Name: argon-88-sk
Version: 0.1.2
Summary: XML & JSON serialization tools at BSUIR 2023 spring semester.
Author: Me
License: MIT
